{
  "version": "6.2.0",
  "flags": {},
  "shapes": [
    {
      "label": "plate",
      "points": [
        [
          309.7567567567568,
          1804.3243243243244
        ],
        [
          235.6267281105991,
          1802.857142857143
        ],
        [
          125.4884792626728,
          1801.4746543778801
        ],
        [
          175.61802575107296,
          275.236051502146
        ],
        [
          300.79376498800957,
          269.3525179856114
        ],
        [
          328.85131894484414,
          268.872901678657
        ],
        [
          366.98081534772183,
          267.4340527577937
        ],
        [
          532.8198198198198,
          258.91891891891896
        ],
        [
          534.8018018018018,
          361.2612612612613
        ],
        [
          555.7358490566038,
          1342.264150943396
        ],
        [
          736.9285714285714,
          1342.857142857143
        ],
        [
          758.270935960591,
          1813.9408866995072
        ],
        [
          373.0,
          1805.6756756756756
        ]
      ],
      "group_id": null,
      "description": "",
      "shape_type": "polygon",
      "flags": {},
      "mask": null
    },
    {
      "label": "paper",
      "points": [
        [
          263.3629032258065,
          1019.0725806451615
        ],
        [
          264.975806451613,
          1143.266129032258
        ],
        [
          442.3951612903226,
          1138.8306451612905
        ],
        [
          437.15322580645164,
          1013.8306451612905
        ]
      ],
      "group_id": null,
      "description": "",
      "shape_type": "polygon",
      "flags": {},
      "mask": null
    }
  ],
  "imagePath": "..\\raw_images\\B2501068-001.jpg",
  "imageData": null,
  "imageHeight": 1920,
  "imageWidth": 886
}